knesset_data_django/__init__.py
knesset_data_django/settings.py
knesset_data_django/committees/__init__.py
knesset_data_django/committees/meetings.py
knesset_data_django/committees/models.py
knesset_data_django/committees/plenum_protocol_parts.py
knesset_data_django/committees/management/__init__.py
knesset_data_django/committees/management/commands/__init__.py
knesset_data_django/committees/management/commands/get_members_attendance.py
knesset_data_django/committees/management/commands/scrape_committee_meetings.py
knesset_data_django/committees/management/commands/scrape_committees.py
knesset_data_django/committees/scrapers/__init__.py
knesset_data_django/committees/scrapers/committee_meetings.py
knesset_data_django/committees/scrapers/committees.py
knesset_data_django/committees/scrapers/members_attendance.py
knesset_data_django/committees/scrapers/tests/__init__.py
knesset_data_django/committees/scrapers/tests/test_committee_meetings.py
knesset_data_django/committees/scrapers/tests/test_committees.py
knesset_data_django/common/__init__.py
knesset_data_django/common/exceptions.py
knesset_data_django/common/management_commands/__init__.py
knesset_data_django/common/management_commands/base_no_args_command.py
knesset_data_django/common/scrapers/__init__.py
knesset_data_django/common/scrapers/base_scraper.py
knesset_data_django/common/testing/__init__.py
knesset_data_django/common/testing/mocks.py
knesset_data_django/common/testing/test_runner.py
knesset_data_django/mks/__init__.py
knesset_data_django/mks/models.py
knesset_data_django/mks/utils.py
knesset_data_django/persons/__init__.py
knesset_data_django/persons/models.py
knesset_data_django-1.3.0.dist-info/DESCRIPTION.rst
knesset_data_django-1.3.0.dist-info/METADATA
knesset_data_django-1.3.0.dist-info/RECORD
knesset_data_django-1.3.0.dist-info/WHEEL
knesset_data_django-1.3.0.dist-info/metadata.json
knesset_data_django-1.3.0.dist-info/top_level.txt
