Metadata-Version: 2.0
Name: knesset-data-django
Version: 1.3.0
Summary: Django apps / modules for handling Israeli parliament (Knesset) data
Home-page: https://github.com/hasadna/knesset-data
Author: Ori Hoch
Author-email: ori@uumpa.com
License: GPLv3
Platform: UNKNOWN
Requires-Dist: django
Requires-Dist: knesset-data
